nuodb_aws_quickstart.py
nuodb_backup.py
nuodb_load.py
nuodb_tarball_installer.py
setup.py
nuodbTools/__init__.py
nuodbTools/exception.py
nuodbTools.egg-info/PKG-INFO
nuodbTools.egg-info/SOURCES.txt
nuodbTools.egg-info/dependency_links.txt
nuodbTools.egg-info/not-zip-safe
nuodbTools.egg-info/requires.txt
nuodbTools.egg-info/top_level.txt
nuodbTools/aws/__init__.py
nuodbTools/aws/host.py
nuodbTools/aws/zone.py
nuodbTools/cluster/__init__.py
nuodbTools/cluster/backup.py
nuodbTools/cluster/cluster.py
nuodbTools/cluster/database.py
nuodbTools/cluster/domain.py
nuodbTools/cluster/load.py
nuodbTools/cluster/sql.py
nuodbTools/cluster/templates/init.py
nuodbTools/physical/__init__.py
nuodbTools/physical/host.py