Metadata-Version: 1.0
Name: nuodbTools
Version: 0.1.1
Summary: Various tools to deploy, manintain and monitor NuoDB
Home-page: http://github.com/nuodb/nuodbTools
Author: NuoDB Inc.
Author-email: info@nuodb.com
License: BSD licence, see LICENCE.txt
Platform: UNKNOWN
